domprob/__init__.py
domprob/base_exc.py
domprob/exceptions.py
domprob/consumers/__init__.py
domprob/consumers/basic.py
domprob/consumers/consumer.py
domprob/dispatchers/__init__.py
domprob/dispatchers/basic.py
domprob/dispatchers/dispatcher.py
domprob/observations/__init__.py
domprob/observations/base.py
domprob/observations/observation.py
domprob/probes/__init__.py
domprob/probes/probe.py
domprob/sensors/__init__.py
domprob/sensors/base_meth.py
domprob/sensors/bound_meth.py
domprob/sensors/dec.py
domprob/sensors/exc.py
domprob/sensors/instrums.py
domprob/sensors/meth.py
domprob/sensors/meth_binder.py
domprob/sensors/meth_meta.py
domprob/sensors/meth_sig.py
domprob/sensors/validate/__init__.py
domprob/sensors/validate/base_val.py
domprob/sensors/validate/chain.py
domprob/sensors/validate/chain_val.py
domprob/sensors/validate/orch.py
domprob/sensors/validate/vals.py
domprob-1.0.0.dist-info/LICENSE
domprob-1.0.0.dist-info/METADATA
domprob-1.0.0.dist-info/WHEEL
domprob-1.0.0.dist-info/top_level.txt
domprob-1.0.0.dist-info/RECORD
