Metadata-Version: 2.2
Name: domprob
Version: 1.0.0
Summary: Python package to implement observability domain probes
License: MIT
Project-URL: Documentation, https://domprob.readthedocs.io/en/latest/
Project-URL: Repository, https://github.com/tenyo-app/pydomprob
Project-URL: Issues, https://github.com/tenyo-app/pydomprob/issues
Keywords: logging,observability,domain-probe
Classifier: Development Status :: 5 - Production/Stable
Classifier: Intended Audience :: Developers
Classifier: Topic :: Software Development :: Libraries
Classifier: Programming Language :: Python :: 3
Classifier: Programming Language :: Python :: 3.10
Classifier: Programming Language :: Python :: 3.11
Classifier: Programming Language :: Python :: 3.12
Classifier: Programming Language :: Python :: 3.13
Classifier: License :: OSI Approved :: MIT License
Requires-Python: <3.14,>=3.10
License-File: LICENSE
